analytics_describe/__init__.py
analytics_plots/__init__.py
analytics_plots/plotter.py
test/__init__.py
test/examples.py
test/notebook_1.py
analytics_insights-0.0.1.dist-info/LICENSE
analytics_insights-0.0.1.dist-info/METADATA
analytics_insights-0.0.1.dist-info/WHEEL
analytics_insights-0.0.1.dist-info/top_level.txt
analytics_insights-0.0.1.dist-info/RECORD
