Metadata-Version: 2.1
Name: analytics-insights
Version: 0.0.1
Summary: A library to produce insights about both Analytics Data and Analytics Deployments
Home-page: https://gde.kapschtraffic.com/brandon/analytics_insights
Author: Alvaro Brandon
Author-email: alvaro.brandon@kapsch.net
License: UNKNOWN
Platform: UNKNOWN
Classifier: Programming Language :: Python :: 3
Classifier: License :: OSI Approved :: MIT License
Classifier: Operating System :: OS Independent
